public class Duff {

    data [I

    public <init>()V  {

        aload 0
        dup
        dup
        invokespecial java/lang/Object.<init>()V

        sipush 100
        newarray I
        putfield Duff.data [I

        iconst 0
        istore 1

        getfield Duff.data [I
    L1:
        dup // Duff.data
        iload 1
        dup
        iastore

        dup // Duff.data
        arraylength 

        iinc 1, [1]
        iload 1

        if_icmpgt L1 // if (Duff.data.length > i) loop again
        
        pop    
        return
    }

    public duffSum()I {
        aload 0
        getfield Duff.data [I
        dup

        // Sum - 1
        // i - 2
        ldc 0
        dup
        istore 1
        istore 2

        // Get array Length
        arraylength // 7
        ldc 8 // 8
        irem // 9

        // [I, 1
        tableswitch END { // 10
            0: EPILOGUE
            1: L7
            2: L6
            3: L5
            4: L4
            5: L3
            6: L2
            7: L1
        }

        // 11

        L0:
            dup // 12
            iload 2 // 13
            iaload // 14
            iload 1 // 15
            iadd // 16
            istore 1 // 17
            iinc 2, [1] // 18
            
        L1:
            dup
            iload 2
            iaload
            iload 1
            iadd
            istore 1
            iinc 2, [1]
        L2:
            dup
            iload 2
            iaload
            iload 1
            iadd
            istore 1
            iinc 2, [1]
        L3:
            dup
            iload 2
            iaload
            iload 1
            iadd
            istore 1
            iinc 2, [1]
        L4:
            dup
            iload 2
            iaload
            iload 1
            iadd
            istore 1
            iinc 2, [1]
        L5:
            dup
            iload 2
            iaload
            iload 1
            iadd
            istore 1
            iinc 2, [1]
        L6:
            dup
            iload 2
            iaload
            iload 1
            iadd
            istore 1
            iinc 2, [1]
        L7:
            dup
            iload 2
            iaload
            iload 1
            iadd
            istore 1
            iinc 2, [1]

        EPILOGUE:
            // [I
            dup
            // [I [I
            arraylength
            // [I 1
            iload 2
            // [I 1 1
            if_icmpgt L0
            // [I
        END:
            iload 1
            ireturn
    }
}
